jaxts/SSM/__init__.py
jaxts/SSM/base.py
jaxts/SSM/dglm.py
jaxts/SSM/dlm.py
jaxts/__init__.py
jaxts-0.0.1.dist-info/LICENSE
jaxts-0.0.1.dist-info/METADATA
jaxts-0.0.1.dist-info/WHEEL
jaxts-0.0.1.dist-info/RECORD
